ATPLibrary/ATPKeywords.py
ATPLibrary/KeyMappings.xml
ATPLibrary/__init__.py
ATPLibrary/version.py
tests/__init__.py
tests/test_ATPKeywords.py
ATPLibrary-0.2.0a24.dist-info/LICENSE.txt
ATPLibrary-0.2.0a24.dist-info/METADATA
ATPLibrary-0.2.0a24.dist-info/WHEEL
ATPLibrary-0.2.0a24.dist-info/top_level.txt
ATPLibrary-0.2.0a24.dist-info/RECORD
