Metadata-Version: 2.1
Name: ATPLibrary
Version: 0.2.0a24
Summary: Robotframework ATP Library
Home-page: https://sqsglobal.visualstudio.com/ATP/_git/ATP.RobotFramework
Author: Wayne Vera
Author-email: wayne.vera@expleogroup.com
License: MIT
Platform: UNKNOWN
Classifier: Programming Language :: Python :: 3
Classifier: License :: OSI Approved :: MIT License
Classifier: Operating System :: OS Independent
Classifier: Framework :: Robot Framework
Classifier: Framework :: Robot Framework :: Library
Classifier: Natural Language :: English
Classifier: Topic :: Software Development :: Testing
Requires-Python: >=3.6
Requires-Dist: requests (>=2)
Requires-Dist: robotframework (>=3)
